generic_parser/__init__.py
generic_parser/dict_parser.py
generic_parser/entry_datatypes.py
generic_parser/entrypoint_parser.py
generic_parser/tools.py
generic_parser-1.1.2.dist-info/METADATA
generic_parser-1.1.2.dist-info/WHEEL
generic_parser-1.1.2.dist-info/licenses/LICENSE
generic_parser-1.1.2.dist-info/RECORD
